MANIFEST.in
README.md
setup.py
Django_SWS_EMSAIU.egg-info/PKG-INFO
Django_SWS_EMSAIU.egg-info/SOURCES.txt
Django_SWS_EMSAIU.egg-info/dependency_links.txt
Django_SWS_EMSAIU.egg-info/requires.txt
Django_SWS_EMSAIU.egg-info/top_level.txt
emsaiu/VERSION
emsaiu/__init__.py
emsaiu/exceptions.py
emsaiu/tests.py
emsaiu/urls.py
emsaiu/resources/gws/file/group_sws/v2/group/u_classrm_services_ems_schedulers/effective_member/javerage
emsaiu/resources/gws/file/group_sws/v3/group/u_classrm_services_ems_schedulers/effective_member/javerage
emsaiu/resources/pws/file/identity/v2/person/C689CB086A7C11D5A4AE0004AC494FFE/full.json
emsaiu/resources/sws/file/student/v5/section.json_quarter_autumn_facility_code_JHN_year_2013
emsaiu/resources/sws/file/student/v5/section.json_quarter_autumn_facility_code_KNE_year_2013
emsaiu/resources/sws/file/student/v5/section.json_quarter_autumn_facility_code_MGH_year_2013
emsaiu/resources/sws/file/student/v5/section.json_quarter_spring_facility_code_JHN_year_2013
emsaiu/resources/sws/file/student/v5/section.json_quarter_spring_facility_code_KNE_year_2013
emsaiu/resources/sws/file/student/v5/section.json_quarter_spring_facility_code_MGH_year_2013
emsaiu/resources/sws/file/student/v5/section.json_quarter_summer_facility_code_JHN_year_2013
emsaiu/resources/sws/file/student/v5/section.json_quarter_summer_facility_code_KNE_year_2013
emsaiu/resources/sws/file/student/v5/section.json_quarter_summer_facility_code_MGH_year_2013
emsaiu/static/emsaiu/css/desktop.less
emsaiu/static/emsaiu/css/mobile.less
emsaiu/static/emsaiu/img/fa-caret-down3.png
emsaiu/static/emsaiu/js/main.js
emsaiu/static/vendor/ico/apple-touch-icon-114-precomposed.png
emsaiu/static/vendor/ico/apple-touch-icon-144-precomposed.png
emsaiu/static/vendor/ico/apple-touch-icon-57-precomposed.png
emsaiu/static/vendor/ico/apple-touch-icon-72-precomposed.png
emsaiu/static/vendor/ico/favicon.ico
emsaiu/static/vendor/js/angular-1.2.13.min.js
emsaiu/static/vendor/js/angular-resource-1.2.13.min.js
emsaiu/static/vendor/js/holder-2.3.1.min.js
emsaiu/static/vendor/js/moment.min.js
emsaiu/static/vendor/less/bordered-pulled.less
emsaiu/static/vendor/less/core.less
emsaiu/static/vendor/less/fixed-width.less
