Metadata-Version: 1.1
Name: Django-SWS-EMSAIU
Version: 0.3
Summary: Django app to aid in the import of the academic schedule from the UW Student Web Service
Home-page: https://github.com/uw-it-cte/django-sws-emsaiu
Author: UNKNOWN
Author-email: UNKNOWN
License: Apache License, Version 2.0
Platform: UNKNOWN
Classifier: Environment :: Web Environment
Classifier: Framework :: Django
Classifier: Intended Audience :: Developers
Classifier: License :: OSI Approved :: Apache Software License
Classifier: Operating System :: OS Independent
Classifier: Programming Language :: Python
Classifier: Programming Language :: Python :: 2.7
Classifier: Programming Language :: Python :: 3.6
